paylink/__init__.py
paylink/paylink.py
paylink/paylink_gateway_order_request.py
paylink/paylink_invoice_response.py
paylink/paylink_product.py
paylink_package-1.0.7.dist-info/LICENSE
paylink_package-1.0.7.dist-info/METADATA
paylink_package-1.0.7.dist-info/WHEEL
paylink_package-1.0.7.dist-info/top_level.txt
paylink_package-1.0.7.dist-info/RECORD
