Metadata-Version: 2.2
Name: paylink_package
Version: 1.0.7
Summary: A Python package designed for seamless integration with the Paylink API, ideal for developers who want to incorporate Paylink's payment processing capabilities into their applications effortlessly. It offers straightforward functionality for adding and retrieving invoices.
Home-page: https://github.com/sultan-algarbi-paylink/python-package.git
Author: Sultan Algarbi
Author-email: sultanye8@gmail.com
License: MIT
License-File: LICENSE
Requires-Dist: requests
Dynamic: author
Dynamic: author-email
Dynamic: description
Dynamic: description-content-type
Dynamic: home-page
Dynamic: license
Dynamic: requires-dist
Dynamic: summary
